{
  "name": "autonomous-sales-sniper",
  "description": "Why wait for leads? This agent reads your target segments from a CSV, hunts for companies in those niches, disqualifies agencies/freelancers, and builds a verified outreach list automatically.",
  "command": "python main.py",
  "inputs": [
    {
      "name": "config.json",
      "description": "Configuration settings.",
      "required": true
    },
    {
      "name": "target_segments.csv",
      "description": "Input data file.",
      "required": true
    }
  ],
  "outputs": []
}